{"type":"Topology","objects":{"Middle_Layer_Super_Output_Areas_December_2011_Generalised_Clipped_Boundaries_in_England_and_Wales_Middle_Layer_Super_Output_Area_2011_to_Ward_2017_Lookup_in_England_and_Wales_LAD17CD_E08000023":{"type":"GeometryCollection","geometries":[{"type":"Polygon","arcs":[[0,1,2,3]],"properties":{"objectid":1721,"msoa11cd":"E02001768","msoa11nm":"South Tyneside 001","msoa11nmw":"South Tyneside 001","st_areasha":1983666.169623,"st_lengths":8816.35961715869,"Middle_Lay":"E08000023","Middle_L_1":"South Tyneside"}},{"type":"Polygon","arcs":[[4,5,6,-3,7]],"properties":{"objectid":1722,"msoa11cd":"E02001769","msoa11nm":"South Tyneside 002","msoa11nmw":"South Tyneside 002","st_areasha":2031452.7426745,"st_lengths":7233.423876049172,"Middle_Lay":"E08000023","Middle_L_1":"South Tyneside"}},{"type":"Polygon","arcs":[[8,9,-8,-2,10]],"properties":{"objectid":1723,"msoa11cd":"E02001770","msoa11nm":"South Tyneside 003","msoa11nmw":"South Tyneside 003","st_areasha":834614.609516,"st_lengths":6277.5353363084505,"Middle_Lay":"E08000023","Middle_L_1":"South Tyneside"}},{"type":"Polygon","arcs":[[11,12,13,14,-11,-1]],"properties":{"objectid":1724,"msoa11cd":"E02001771","msoa11nm":"South Tyneside 004","msoa11nmw":"South Tyneside 004","st_areasha":2285226.9413505,"st_lengths":7911.9593498427375,"Middle_Lay":"E08000023","Middle_L_1":"South Tyneside"}},{"type":"Polygon","arcs":[[15,16,17,-5,-10]],"properties":{"objectid":1725,"msoa11cd":"E02001772","msoa11nm":"South Tyneside 005","msoa11nmw":"South Tyneside 005","st_areasha":1225894.2219665,"st_lengths":6147.951141460262,"Middle_Lay":"E08000023","Middle_L_1":"South Tyneside"}},{"type":"Polygon","arcs":[[-15,18,19,20,-16,-9]],"properties":{"objectid":1726,"msoa11cd":"E02001773","msoa11nm":"South Tyneside 006","msoa11nmw":"South Tyneside 006","st_areasha":1256410.9618925,"st_lengths":8285.980874335875,"Middle_Lay":"E08000023","Middle_L_1":"South Tyneside"}},{"type":"MultiPolygon","arcs":[[[21,22,23]],[[24,25,26]],[[27,28]]],"properties":{"objectid":1727,"msoa11cd":"E02001774","msoa11nm":"South Tyneside 007","msoa11nmw":"South Tyneside 007","st_areasha":3270499.336649,"st_lengths":14436.512498142856,"Middle_Lay":"E08000023","Middle_L_1":"South Tyneside"}},{"type":"Polygon","arcs":[[29,30,-19,-14]],"properties":{"objectid":1728,"msoa11cd":"E02001775","msoa11nm":"South Tyneside 008","msoa11nmw":"South Tyneside 008","st_areasha":866713.1355855,"st_lengths":5025.711546910783,"Middle_Lay":"E08000023","Middle_L_1":"South Tyneside"}},{"type":"Polygon","arcs":[[-23,31,32,33,34]],"properties":{"objectid":1729,"msoa11cd":"E02001776","msoa11nm":"South Tyneside 009","msoa11nmw":"South Tyneside 009","st_areasha":1955443.81138,"st_lengths":7476.874712478402,"Middle_Lay":"E08000023","Middle_L_1":"South Tyneside"}},{"type":"Polygon","arcs":[[-34,35,36]],"properties":{"objectid":1730,"msoa11cd":"E02001777","msoa11nm":"South Tyneside 010","msoa11nmw":"South Tyneside 010","st_areasha":2046107.543882,"st_lengths":9275.19101999576,"Middle_Lay":"E08000023","Middle_L_1":"South Tyneside"}},{"type":"Polygon","arcs":[[37,38,39,-18]],"properties":{"objectid":1731,"msoa11cd":"E02001778","msoa11nm":"South Tyneside 011","msoa11nmw":"South Tyneside 011","st_areasha":1056565.750127,"st_lengths":4806.792110674069,"Middle_Lay":"E08000023","Middle_L_1":"South Tyneside"}},{"type":"Polygon","arcs":[[-40,40,41,42,-25,43,-28,44,-6]],"properties":{"objectid":1732,"msoa11cd":"E02001779","msoa11nm":"South Tyneside 012","msoa11nmw":"South Tyneside 012","st_areasha":2690614.1711245,"st_lengths":11616.433903485693,"Middle_Lay":"E08000023","Middle_L_1":"South Tyneside"}},{"type":"Polygon","arcs":[[45,46,-20,-31,47]],"properties":{"objectid":1733,"msoa11cd":"E02001780","msoa11nm":"South Tyneside 013","msoa11nmw":"South Tyneside 013","st_areasha":1200680.5973485,"st_lengths":5563.595612205217,"Middle_Lay":"E08000023","Middle_L_1":"South Tyneside"}},{"type":"Polygon","arcs":[[48,49,50,-42]],"properties":{"objectid":1734,"msoa11cd":"E02001781","msoa11nm":"South Tyneside 014","msoa11nmw":"South Tyneside 014","st_areasha":1156689.77011,"st_lengths":5964.95393950799,"Middle_Lay":"E08000023","Middle_L_1":"South Tyneside"}},{"type":"Polygon","arcs":[[-33,51,52,53,-36]],"properties":{"objectid":1735,"msoa11cd":"E02001782","msoa11nm":"South Tyneside 015","msoa11nmw":"South Tyneside 015","st_areasha":3251185.93665,"st_lengths":9909.030042246044,"Middle_Lay":"E08000023","Middle_L_1":"South Tyneside"}},{"type":"Polygon","arcs":[[54,55,56,57,-49,-41,-39]],"properties":{"objectid":1736,"msoa11cd":"E02001783","msoa11nm":"South Tyneside 016","msoa11nmw":"South Tyneside 016","st_areasha":1483443.7248395,"st_lengths":7202.287321670939,"Middle_Lay":"E08000023","Middle_L_1":"South Tyneside"}},{"type":"Polygon","arcs":[[-43,-51,58,-52,-32,-22,59,-26]],"properties":{"objectid":1737,"msoa11cd":"E02001784","msoa11nm":"South Tyneside 017","msoa11nmw":"South Tyneside 017","st_areasha":2326151.4471805,"st_lengths":8055.587806041171,"Middle_Lay":"E08000023","Middle_L_1":"South Tyneside"}},{"type":"Polygon","arcs":[[60,61,-48,-30,-13,62]],"properties":{"objectid":1738,"msoa11cd":"E02001785","msoa11nm":"South Tyneside 018","msoa11nmw":"South Tyneside 018","st_areasha":6568485.007101,"st_lengths":14790.646490639228,"Middle_Lay":"E08000023","Middle_L_1":"South Tyneside"}},{"type":"Polygon","arcs":[[-55,-38,-17,-21,-47,63]],"properties":{"objectid":1739,"msoa11cd":"E02001786","msoa11nm":"South Tyneside 019","msoa11nmw":"South Tyneside 019","st_areasha":1960489.4539655,"st_lengths":5855.92368516125,"Middle_Lay":"E08000023","Middle_L_1":"South Tyneside"}},{"type":"Polygon","arcs":[[64,65,66,-53,-59]],"properties":{"objectid":1740,"msoa11cd":"E02001787","msoa11nm":"South Tyneside 020","msoa11nmw":"South Tyneside 020","st_areasha":8044614.794628,"st_lengths":12736.168644435736,"Middle_Lay":"E08000023","Middle_L_1":"South Tyneside"}},{"type":"Polygon","arcs":[[-65,-50,-58,67]],"properties":{"objectid":1741,"msoa11cd":"E02001788","msoa11nm":"South Tyneside 021","msoa11nmw":"South Tyneside 021","st_areasha":2083970.8758065,"st_lengths":6319.537619389522,"Middle_Lay":"E08000023","Middle_L_1":"South Tyneside"}},{"type":"Polygon","arcs":[[68,-56,-64,-46,-62]],"properties":{"objectid":1742,"msoa11cd":"E02001789","msoa11nm":"South Tyneside 022","msoa11nmw":"South Tyneside 022","st_areasha":6376318.6944755,"st_lengths":17050.233255035848,"Middle_Lay":"E08000023","Middle_L_1":"South Tyneside"}},{"type":"Polygon","arcs":[[-61,69,-66,-68,-57,-69]],"properties":{"objectid":1743,"msoa11cd":"E02001790","msoa11nm":"South Tyneside 023","msoa11nmw":"South Tyneside 023","st_areasha":8488278.5429155,"st_lengths":24892.707266828733,"Middle_Lay":"E08000023","Middle_L_1":"South Tyneside"}}]}},"arcs":[[[-1.408327214808696,54.99645101793949],[-1.411913611156721,54.99448397629439],[-1.412441163353554,54.994782602080704],[-1.41297436831079,54.9944444910398],[-1.414903678106454,54.9929491159853],[-1.415184845422236,54.99276044531368]],[[-1.415184845422236,54.99276044531368],[-1.417331895852842,54.99322435069546],[-1.420027574286927,54.99286008424949],[-1.426282091390595,54.991367974803055],[-1.427245603238638,54.9911059030128],[-1.427433589797961,54.99104211040891]],[[-1.427433589797961,54.99104211040891],[-1.42751039486516,54.99112087676576],[-1.428605726234403,54.99268648733602],[-1.428915337458378,54.99318386472083],[-1.430212235802709,54.99573742615796],[-1.4303675524247,54.99602928184383],[-1.432293115721483,54.99872406525494],[-1.433682484685289,55.000127962280594],[-1.433782886802752,55.00024161080806],[-1.433850839725481,55.00032391717908],[-1.434825640156219,55.00185475855258],[-1.435744620097499,55.0029882438492],[-1.437270771139489,55.00439413929338],[-1.437996404984694,55.00482666876198]],[[-1.437996404984694,55.00482666876198],[-1.433262223368397,55.00629818336309],[-1.433689785801488,55.006468216405736],[-1.43297962531931,55.00638133742461],[-1.428289882336723,55.0074323467459],[-1.428193396830442,55.0068504772737],[-1.427508204600189,55.00676728728067],[-1.426461276355233,55.00771129872405],[-1.423904534717008,55.008173689295084],[-1.42392377159715,55.00792216751123],[-1.425247248591143,55.007762182642914],[-1.425341215466931,55.00742294880761],[-1.423900799553799,55.005635849792576],[-1.420299354705682,55.00369853160482],[-1.418657844741991,55.00326296250557],[-1.40956875992463,55.00835835932999],[-1.403363616323801,55.00979283713605],[-1.4017630487884,55.010595527740456],[-1.401301386220922,55.011357079319474],[-1.400875255680458,55.01131912683985],[-1.401461351074732,55.01048464645602],[-1.402868837702821,55.00974570354567],[-1.409624756844953,55.00805850274076],[-1.413002843738209,55.00617967070242],[-1.414576619683297,55.00450414858756],[-1.412270623600989,55.00043398340878],[-1.408327214808696,54.99645101793949]],[[-1.431337855370782,54.98613807525781],[-1.432218787627993,54.985908465604986],[-1.432818822574683,54.984973352860884],[-1.433958299318975,54.98428444882898],[-1.435560744041653,54.98318423629475],[-1.437029959441305,54.9812925045417],[-1.43842593903848,54.97961943474196]],[[-1.43842593903848,54.97961943474196],[-1.440402687954913,54.98034603691469],[-1.440665902627813,54.980448460050994],[-1.441230430325589,54.98060262559488],[-1.441755795581306,54.98067982939655],[-1.442471936031519,54.98184592800572],[-1.44433053338,54.984106980291976],[-1.444737244809657,54.98657072957802],[-1.44608887366505,54.98666991891771],[-1.446235896489855,54.98632012868249],[-1.448080544990941,54.986291629757176]],[[-1.448080544990941,54.986291629757176],[-1.447537871176756,54.986423991819215],[-1.449397844526421,54.98719894755817],[-1.447626867050117,54.98916163504929],[-1.446954213663857,54.989435363336334],[-1.447108176192413,54.9897191317534],[-1.444219558267882,54.99291950877747],[-1.443459110701036,54.99320629796769],[-1.443809539641524,54.9934091910451],[-1.441411683927837,54.9954793650213],[-1.439870038985517,54.99761653313336],[-1.439842553446406,55.000598968471856],[-1.440329553661801,55.000990308923186],[-1.44041449019411,55.00286433419655],[-1.439149095683383,55.00447874386385],[-1.437996404984694,55.00482666876198]],[[-1.427433589797961,54.99104211040891],[-1.425636496736405,54.98949954181902],[-1.424573093844425,54.98872064646657],[-1.424050183102614,54.98834700815641],[-1.422962579496398,54.98751632340758],[-1.424040778998382,54.98676801773376],[-1.42479129717021,54.986501120737564],[-1.427584135587931,54.98646846978834],[-1.427963198643198,54.986467730151944],[-1.431155620242301,54.986180666614786],[-1.431337855370782,54.98613807525781]],[[-1.410824465222283,54.98506329334503],[-1.410477572974347,54.98433540850579],[-1.4140166044832,54.98316366324774],[-1.414562949137257,54.98320224344904],[-1.415394681208205,54.98403296865278],[-1.416599175671883,54.98366034589342],[-1.415286691067994,54.98413712291546],[-1.415796776143462,54.98492317501595],[-1.41337579568181,54.98560973150004],[-1.41411561519257,54.98586527632374],[-1.413818447451625,54.98640325740957],[-1.414574863615974,54.98640854879243],[-1.415171951983063,54.986002621590195],[-1.416774543140126,54.98575790676452],[-1.417038195072561,54.98599986703946],[-1.416441675640027,54.98618571420587],[-1.417691124350303,54.98731498265113],[-1.419120635411066,54.98680059325174],[-1.417948525102114,54.98572564443188],[-1.421450909745966,54.984502170163545],[-1.420339402369047,54.9832980138209],[-1.420340872734979,54.98254068247808]],[[-1.420340872734979,54.98254068247808],[-1.421206519429558,54.98235916469053],[-1.422365851259278,54.9816521303276],[-1.423515291398563,54.98066745741168],[-1.425086174263995,54.98176671905367],[-1.427196884929933,54.983312914554084],[-1.427477662793678,54.983516433583816],[-1.42778723177146,54.98373719667097],[-1.430068876517097,54.985387888638506],[-1.430234045478231,54.98550859166973],[-1.431337855370782,54.98613807525781]],[[-1.415184845422236,54.99276044531368],[-1.414852379552656,54.99265254027707],[-1.415134994262601,54.992514720598045],[-1.416603864792035,54.99200473203362],[-1.416659302423883,54.991956157748376],[-1.416179930083263,54.991397618175974],[-1.41559278955904,54.990715742096306],[-1.414840665250056,54.98982412165303],[-1.414270558549795,54.98913463014417],[-1.41314853396,54.98852382148308],[-1.411307932103967,54.986178022400445],[-1.410784553145904,54.98576584406373],[-1.410824465222283,54.98506329334503]],[[-1.408327214808696,54.99645101793949],[-1.403704728870214,54.99342172075177],[-1.403086668752499,54.99325693924618],[-1.402100538121504,54.99377599180295],[-1.401465728980141,54.99326605041201],[-1.400763564454739,54.993292247526725],[-1.401330017795307,54.992407202848185],[-1.399195309424477,54.99165621599297],[-1.397995450908112,54.99183472465085],[-1.396595129179218,54.99146108652633],[-1.395160627258019,54.990982016007905],[-1.394038744607943,54.99106697678815],[-1.39448870030215,54.98993538541655],[-1.393631902405216,54.989232890128484],[-1.393421190777846,54.988177759367424],[-1.392117768138604,54.98807869435332],[-1.388785501036341,54.988930959364325],[-1.388115852752007,54.98805593193586],[-1.386817819576917,54.987911906281106],[-1.386368550032594,54.98734620629608],[-1.385762388768573,54.987436603066264],[-1.385594463185516,54.986868726173554],[-1.385029093007247,54.986849738720394],[-1.385545176186796,54.98651531980291],[-1.385161631549052,54.98614944075253],[-1.384082491757144,54.98620688401483],[-1.382988680581805,54.98589580921199],[-1.382319705936717,54.98610898085673],[-1.381454184263076,54.9858907106084],[-1.381422730287645,54.98549784485602],[-1.380658893923506,54.9856808794096],[-1.381244548414096,54.985093467203356],[-1.380110939398198,54.98452875303914],[-1.380605105388441,54.98419968002092],[-1.380346545213784,54.98353607999168],[-1.381726740062178,54.982897894953595],[-1.382079620556497,54.981998372053454],[-1.38089070092402,54.98025430318434]],[[-1.38089070092402,54.98025430318434],[-1.382636289327301,54.97936152772978],[-1.383465531063197,54.97889742714187],[-1.384420291966408,54.97830148159201],[-1.384489950920423,54.97825805335217]],[[-1.384489950920423,54.97825805335217],[-1.389866143046736,54.979032273032054],[-1.392264604842143,54.97935332227874],[-1.393274667861257,54.97948852001599],[-1.397242693022439,54.98027546202622],[-1.397576531331037,54.98039342460724],[-1.399478077205312,54.980782288437034]],[[-1.399478077205312,54.980782288437034],[-1.399167307815587,54.98079835807813],[-1.400664924035907,54.98127909666532],[-1.40233703161097,54.98242197595201],[-1.402191377123896,54.982926487605965],[-1.403909828025134,54.983792624628826],[-1.403617936283124,54.98328177594411],[-1.402890697794424,54.98297154028558],[-1.403397545347863,54.982529246654586],[-1.405410830169152,54.98303073396593],[-1.405036799559563,54.98354946554443],[-1.405280860691724,54.98428057194538],[-1.40953085573636,54.985370605908756],[-1.409721522456783,54.98512623208637],[-1.410824465222283,54.98506329334503]],[[-1.420340872734979,54.98254068247808],[-1.419601352465356,54.98258111390012],[-1.417078796313686,54.9809399261159],[-1.415237581978587,54.97948109328747],[-1.415550789535943,54.978851615178954],[-1.416530909380728,54.97897576356997],[-1.417928823227898,54.9784607003029],[-1.41829207681036,54.9776567468563],[-1.418549652785669,54.97760250049122],[-1.41859700962644,54.97760133308889],[-1.419174939211741,54.97762575868013],[-1.420118230208764,54.97830422287641],[-1.42052546502753,54.97813421002883],[-1.419668734917129,54.977848534224485],[-1.41934530820784,54.97712918882115],[-1.418336812500375,54.9768995577676],[-1.41889797539456,54.976383416821186],[-1.422134876807557,54.975959603515214],[-1.420601086999027,54.97433082409331],[-1.419274859567065,54.97291672312509],[-1.418530557889006,54.97299414746782],[-1.417105987720391,54.97181732668382]],[[-1.417105987720391,54.97181732668382],[-1.420928267516197,54.97088515954916],[-1.424550920704353,54.9699830327933]],[[-1.424550920704353,54.9699830327933],[-1.425509922173564,54.971270767181146],[-1.425617659239672,54.9714133045675],[-1.426462622244725,54.97247323514301],[-1.429138247629436,54.97400045166946],[-1.428816089758673,54.97423224932874],[-1.429931021852866,54.974687399167],[-1.431043756533432,54.97597612427408],[-1.432428024170274,54.97767796638457],[-1.433022668180066,54.97757681893996],[-1.43330442514461,54.97795637298059],[-1.433530961129067,54.97822681802331],[-1.433068856219847,54.97853917045625],[-1.436561658421408,54.97910963109678],[-1.43842593903848,54.97961943474196]],[[-1.399478077205312,54.980782288437034],[-1.399995299817145,54.980827965544975],[-1.402072855778722,54.98085630576901],[-1.406421115881534,54.98050595959792],[-1.407117403693982,54.98043720502051],[-1.407772261664426,54.980287089694855],[-1.405886369957478,54.97808061142295],[-1.406217808489978,54.97796777544879],[-1.405997301471333,54.97774377864303],[-1.404795929268358,54.97799395207642],[-1.40497332578806,54.97693775000495],[-1.403979515195565,54.976954673482055],[-1.404254067004838,54.976323289235076],[-1.405634436395997,54.97613329177752],[-1.405204605150393,54.97551932018368],[-1.405509580983362,54.97514262621826],[-1.405827513025874,54.974773727870364],[-1.406809823857291,54.974637652239515],[-1.407335003549697,54.9748364306287],[-1.407749999459812,54.97449908160064],[-1.407247076509031,54.97441116173858],[-1.407474073143192,54.97392175796192],[-1.406796477024541,54.973636140911076],[-1.408388146801141,54.97293552767303],[-1.408997220666504,54.97305218286592],[-1.409325890786363,54.972716845279784],[-1.410792864425908,54.972553272286895],[-1.410589966922273,54.97167097536434]],[[-1.410589966922273,54.97167097536434],[-1.410809599075227,54.97167454259317],[-1.415762499025342,54.97188683239195],[-1.416720243592278,54.97191777747194]],[[-1.416720243592278,54.97191777747194],[-1.417105987720391,54.97181732668382]],[[-1.48042642098503,54.974948939959376],[-1.484410041463411,54.9746931401957],[-1.485007604327998,54.97403838175881],[-1.485962103876795,54.97426835619476],[-1.486172855530528,54.97366716218039],[-1.487095789506954,54.97350552377237],[-1.486942282893691,54.97376929965038],[-1.488680359773006,54.974427351322134],[-1.490887864907043,54.97265322789506],[-1.490769329772996,54.97205209636232],[-1.489996214117473,54.97205413682391],[-1.489259430413224,54.97158024775774],[-1.490409801254961,54.97089297595048],[-1.492728422747875,54.97112005106142]],[[-1.492728422747875,54.97112005106142],[-1.492721532815951,54.97195867870249],[-1.493322708066763,54.97439523871895],[-1.493330767263045,54.974426391810916],[-1.493858987027793,54.97621871369853],[-1.495324575008217,54.976087249286444],[-1.495613708343749,54.97705842841416],[-1.495971282314424,54.97849779754767],[-1.496036363173815,54.978760457775984],[-1.496500067507266,54.980684777983136],[-1.50104856124174,54.98132803597677],[-1.501946124792272,54.98194690902265],[-1.503766697001198,54.98249723164765],[-1.503980553516403,54.984046555015766],[-1.505086732132234,54.984071836007104],[-1.506407823796064,54.986059338271815]],[[-1.506407823796064,54.986059338271815],[-1.505278735126552,54.98586874623929],[-1.503946904086995,54.98615538857164],[-1.493535446413617,54.98624872945568],[-1.491991284604791,54.98586081630808],[-1.487620145762797,54.98600876257836],[-1.479837356602955,54.98569541285772],[-1.475585451907446,54.98652639090977],[-1.472304639916592,54.98622286554858],[-1.472578764726399,54.9843845551308],[-1.469473103467834,54.98076665947751],[-1.4701913928878,54.980088622670046],[-1.473536715534972,54.97959804104679],[-1.47661314514904,54.978639939573455],[-1.476983124320038,54.97782196748758],[-1.478058420024925,54.97743028283055],[-1.478837587379396,54.97581496710528],[-1.48042642098503,54.974948939959376]],[[-1.458511465783719,54.97908379498696],[-1.458161283044296,54.97690066319231],[-1.458151928831942,54.97678081585107],[-1.458236329369174,54.97631390218859],[-1.460085657980817,54.97613478470599],[-1.460705473208629,54.974742115414074],[-1.461544360098482,54.97469825318927],[-1.462734627901222,54.97367322651075],[-1.465615493106322,54.974430507141555],[-1.471558778587659,54.97542899914591],[-1.472326014852224,54.97529739546873],[-1.473178831466037,54.973998078753205],[-1.474523998547079,54.97434564795629],[-1.476821922791026,54.97406926187105]],[[-1.476821922791026,54.97406926187105],[-1.478754920205704,54.97576361603839]],[[-1.478754920205704,54.97576361603839],[-1.477937554559745,54.977353381207905],[-1.476918048566912,54.9776599343505],[-1.476486228437974,54.97854772480161],[-1.473395450338733,54.9794599757596],[-1.472105254973973,54.9795892492851],[-1.469964613444895,54.979868378989316],[-1.465852588782411,54.97949095562747],[-1.464277370423166,54.9790690945705],[-1.463513539459614,54.979146385049845],[-1.463017335340876,54.979566555739915],[-1.458511465783719,54.97908379498696]],[[-1.456582928219545,54.98559303106166],[-1.45654277186102,54.984989932686766],[-1.457157318306346,54.984389483937896],[-1.456873845295219,54.9805432698562],[-1.458515924578674,54.97922852159546]],[[-1.458515924578674,54.97922852159546],[-1.463056289839844,54.97969163733362],[-1.464259272594156,54.97917277104797],[-1.465738847948094,54.97958482216602],[-1.4696714007152,54.98009169791041],[-1.469291399517541,54.98115677280334],[-1.472242635085206,54.98463561479101],[-1.471891990205938,54.98611144453165],[-1.464762523436423,54.983799603461144],[-1.460058852716217,54.98451752104657],[-1.456582928219545,54.98559303106166]],[[-1.384489950920423,54.97825805335217],[-1.386489701393166,54.977062527128076],[-1.389102179156243,54.975666297085056],[-1.389793386821583,54.97543734478055],[-1.390489784303244,54.975207677533085],[-1.393093219059419,54.974576108801344],[-1.396671542957859,54.97380293679351]],[[-1.396671542957859,54.97380293679351],[-1.3976791397845,54.97359247799161],[-1.398047950184075,54.97352127882689],[-1.400929997271129,54.97307638824767],[-1.401739145406121,54.97296861917795],[-1.403750561601413,54.972657734470644],[-1.405056785242466,54.972431232864416],[-1.40601374051182,54.97225557086661],[-1.408687949912673,54.97179626095432],[-1.410419337689497,54.97165578227208],[-1.410589966922273,54.97167097536434]],[[-1.492728422747875,54.97112005106142],[-1.49292482304017,54.96966066517362],[-1.492901494158715,54.96925359592985]],[[-1.492901494158715,54.96925359592985],[-1.495297561731919,54.96853341957936],[-1.495700072643758,54.96879658847713],[-1.496313801314792,54.968624901535],[-1.497557881538775,54.96894265570701],[-1.497082805043444,54.97132343183614],[-1.499499327756218,54.971301591496506],[-1.499080150180366,54.972332187616914],[-1.502402461240899,54.971868226969725],[-1.504497587347004,54.97143798336544],[-1.506561828665188,54.9703361321575],[-1.507000534520218,54.970423233107645],[-1.507519197637973,54.97132064388175],[-1.510364612183581,54.9741144544477]],[[-1.510364612183581,54.9741144544477],[-1.511367822796336,54.974883501546216],[-1.512630382238519,54.97498508855828],[-1.514229535571146,54.97463328129625],[-1.514931063441056,54.9751045663418],[-1.515726705692167,54.9752260262794],[-1.516408145891347,54.97572297737425],[-1.51805739592008,54.9749836510642],[-1.518367147364713,54.975209532102156],[-1.518894688151678,54.97496731359928],[-1.519265792252815,54.97512533567077],[-1.519734322121116,54.97619968327434],[-1.517505023115575,54.977341492339924],[-1.517913766729236,54.977714044887286],[-1.517335259489289,54.97808258232603],[-1.518891456585838,54.97905386697955],[-1.518411946682137,54.979307444989175],[-1.518690599993268,54.979524215155124],[-1.519146477382086,54.97929237051223],[-1.520863582394461,54.98022431713724],[-1.520223783421605,54.98067151043924],[-1.520575664494766,54.98130193201015],[-1.519271433962768,54.981916850350714],[-1.518690244225149,54.98151874969964],[-1.516234540381693,54.98206501878086],[-1.516272867585038,54.982992229354586],[-1.515616391622368,54.98310654297564],[-1.516651597437857,54.98539315994113],[-1.516045584774492,54.9854310234006],[-1.516030433864523,54.98587395848956]],[[-1.516030433864523,54.98587395848956],[-1.511038289568327,54.986176844984755],[-1.510964146872881,54.98597615404093],[-1.509583967612515,54.986017563581306],[-1.506407823796064,54.986059338271815]],[[-1.510364612183581,54.9741144544477],[-1.51361099419161,54.973432700617586],[-1.513231372862844,54.97308617446087],[-1.512056810871301,54.97201400507672],[-1.513087472199686,54.971676038686894],[-1.514267797899509,54.972246885614325],[-1.51566731300355,54.97187028861972],[-1.517780868299037,54.971187618659776],[-1.518140534118868,54.9710570063444],[-1.51746498294842,54.970569046830136],[-1.517564163809052,54.96981651548293],[-1.517620679367108,54.96957961838467],[-1.520840716392091,54.96977977059092],[-1.521119559795857,54.96841889764579],[-1.522863382551453,54.96848841343735],[-1.52316396222231,54.967753568846554],[-1.523868941908176,54.96613746458554],[-1.524702864392876,54.96393436205906],[-1.52538844285476,54.96193976927243],[-1.525448967380965,54.9617566308474],[-1.525871588838612,54.96108556251258],[-1.530445469168618,54.958208585017864]],[[-1.530445469168618,54.958208585017864],[-1.530011416233456,54.96048049319138],[-1.529351709465265,54.96273652148856],[-1.529180040953607,54.96330174206396],[-1.531034571751017,54.96430745412433],[-1.534172748300372,54.96509850500015],[-1.532706068506642,54.96967406762827],[-1.532681868228218,54.97263235641354],[-1.532293923965772,54.975706601928806],[-1.531603135531986,54.97827866661322],[-1.53029517021494,54.97978888125652],[-1.530080716708593,54.980614628814045],[-1.528388211742891,54.982112386416055],[-1.528004073878943,54.98195724471007],[-1.527542341390268,54.982557536030356],[-1.526206261781221,54.982963025459625],[-1.526518822858205,54.9832257389942],[-1.526056180137055,54.98354808537664],[-1.524259670339511,54.984255759484064],[-1.523286757753839,54.98420343532937],[-1.522892194366734,54.98466649075799],[-1.521986189969574,54.98490196886795],[-1.519196206838787,54.98547870395641],[-1.518497061914731,54.985268363735706],[-1.518064415488374,54.98564317853117],[-1.517050124248861,54.985520546670024],[-1.516030433864523,54.98587395848956]],[[-1.424550920704353,54.9699830327933],[-1.433307490537558,54.967999115525195],[-1.433652188834506,54.96792400009739],[-1.436383697921769,54.967435015640795],[-1.436761023121737,54.96736487218026],[-1.43706760732518,54.967302389132556],[-1.437835927597309,54.967145804808546],[-1.439056472896785,54.9669558862279]],[[-1.439056472896785,54.9669558862279],[-1.443155182187795,54.96619840133333],[-1.444388185690442,54.9679130527532],[-1.443358343609346,54.967708633002985],[-1.442749532583485,54.968736121738935],[-1.441866636379275,54.96910710202415],[-1.441754520078772,54.96950866369335],[-1.44097625567422,54.969648009238206],[-1.441215344484235,54.970090301059166],[-1.442336487973125,54.97026476548593],[-1.442579264266953,54.97092491836215],[-1.442025907427033,54.97123537630093],[-1.441657923720418,54.97105243370702],[-1.441654420598976,54.971355634784956],[-1.44081320644303,54.971599965409936],[-1.441301560060623,54.97175666604354],[-1.442293507899156,54.972908970143095],[-1.443517029534189,54.973437001869776]],[[-1.443517029534189,54.973437001869776],[-1.44216958491487,54.97545130320539],[-1.440526395209507,54.97718201098583],[-1.439634904136779,54.97816880076903],[-1.438875357459331,54.979082091256835],[-1.43842593903848,54.97961943474196]],[[-1.443517029534189,54.973437001869776],[-1.443742041959533,54.97315282235176],[-1.445933268521211,54.97049834348537],[-1.447427600719671,54.96876204031133],[-1.447661945999638,54.96846990693218],[-1.449040606362026,54.96666150914268],[-1.450571983396713,54.96473663019698],[-1.451028293826974,54.9646546316646],[-1.454362005475055,54.96430601934187],[-1.456474416249535,54.96469889461827],[-1.457433454104278,54.96494602688931]],[[-1.457433454104278,54.96494602688931],[-1.456334156080781,54.96537830120677],[-1.455991319530354,54.96558780559807],[-1.456500471286373,54.96602579965513],[-1.455655226157519,54.965912885570994],[-1.453734777511317,54.966581506702155],[-1.45358281993391,54.96694733306551],[-1.454347445776668,54.96704928747234],[-1.454160107259421,54.96724506919932],[-1.454817961252635,54.96754685662354],[-1.454402669904997,54.9679696105886],[-1.453754012530377,54.96779904482657],[-1.453386282014625,54.968535011912756],[-1.45363383706403,54.96886817701877],[-1.454270029003341,54.96877841611572],[-1.454243037574871,54.96910336706513],[-1.453303914087499,54.96938078711471],[-1.454271812272934,54.969899514992974],[-1.454767842376067,54.9694059062977],[-1.45529459136874,54.96961381679128],[-1.456816734931966,54.96928783273447],[-1.456470440001764,54.968780464711585],[-1.457545672999848,54.96844032675412],[-1.458277339858528,54.96839657578144],[-1.457974450447056,54.96865086260294],[-1.458701216907864,54.96907410732412],[-1.46017589518481,54.970316983738236],[-1.460321570742545,54.970990786763934],[-1.464934469745675,54.969136616303466],[-1.466725674284407,54.96823924244084],[-1.467546403483589,54.96814144931245],[-1.467013034182121,54.96899559518801],[-1.467954100880959,54.96935167747599],[-1.468527820530022,54.96920612342315],[-1.468571210358609,54.96884187191902],[-1.469393947380213,54.96910440913359],[-1.469942518260759,54.96885145100781],[-1.470563545146303,54.969199442985506],[-1.47116678367383,54.96894269109898],[-1.470383964123535,54.96849130293809],[-1.470843113983278,54.9680278423988],[-1.472506259539669,54.967617174173114],[-1.473542412330697,54.968933086787224],[-1.474095659156494,54.96873853238606],[-1.4741599475976,54.96907367662213],[-1.474939918047337,54.96907927902871]],[[-1.474939918047337,54.96907927902871],[-1.475229527214489,54.9699784142919],[-1.475294172007137,54.97017922272808],[-1.476821922791026,54.97406926187105]],[[-1.458511465783719,54.97908379498696],[-1.456856676122699,54.97863970995946],[-1.456619458673912,54.97711546943687],[-1.456472392316843,54.97886624848486],[-1.458515924578674,54.97922852159546]],[[-1.456582928219545,54.98559303106166],[-1.45140255102968,54.98641899234122],[-1.450779233080104,54.98548789585351],[-1.45032956898147,54.98603133766321],[-1.450279432844731,54.98489702737402],[-1.44972023474916,54.98533574007471],[-1.449526096970972,54.98433558220064],[-1.449484340512879,54.985332876799745],[-1.448080544990941,54.986291629757176]],[[-1.396499901450672,54.96898465238869],[-1.395738758518832,54.967778650027846],[-1.396646993489728,54.96762241896588],[-1.396202902314892,54.96371001842982],[-1.397198291906971,54.96363492672104],[-1.397779045599704,54.964841105716594],[-1.398832592233591,54.96456834426196],[-1.4032445800957,54.96423622138719],[-1.406110506874327,54.963852996576655],[-1.405829209834365,54.96291364868999],[-1.407200909472659,54.96273663876565],[-1.407477900778597,54.96363103941053],[-1.40889926372629,54.9635032634777],[-1.413888481528719,54.963090750050945]],[[-1.413888481528719,54.963090750050945],[-1.414268833241784,54.96425448877428],[-1.416047685039558,54.96997414463064],[-1.416720243592278,54.97191777747194]],[[-1.396671542957859,54.97380293679351],[-1.396865020295471,54.97340172900349],[-1.397810091437238,54.97324318767064],[-1.396807248166786,54.97308692925582],[-1.396596749718973,54.97279350617554],[-1.395779282430623,54.97263049301197],[-1.394451518981363,54.97290186283617],[-1.394433173123222,54.971599696207356],[-1.393877407182955,54.97120969258882],[-1.394186529384942,54.970864393765055],[-1.393621514371946,54.97066721710799],[-1.394041890425159,54.97023447802735],[-1.396845930725286,54.96996453124699],[-1.397439580386909,54.97022879224257],[-1.397855494374668,54.969848029132876],[-1.397202962012875,54.96961374506554],[-1.39744686426881,54.969161643032294],[-1.396499901450672,54.96898465238869]],[[-1.457433454104278,54.96494602688931],[-1.457484465147176,54.964959895403446],[-1.457557135959651,54.96442449817819],[-1.458346129316347,54.96415424082398],[-1.459177234416119,54.9635525962071],[-1.45758877855594,54.960576442431986],[-1.459135645458056,54.96006778441299],[-1.460381364918833,54.959649271747985],[-1.460404742294523,54.959543264507474]],[[-1.460404742294523,54.959543264507474],[-1.464753410786423,54.9591810745982],[-1.467301103994681,54.958979188082594],[-1.471251286048276,54.958662516481084]],[[-1.471251286048276,54.958662516481084],[-1.471385431822776,54.960302423606],[-1.472308719082488,54.96243138283814],[-1.473324421354293,54.96459248230389],[-1.473573649532525,54.965162951893475],[-1.473693811620243,54.965452606475026],[-1.474112355432621,54.96626607786739],[-1.474939918047337,54.96907927902871]],[[-1.492901494158715,54.96925359592985],[-1.492408081051148,54.96617994622798],[-1.492165765648531,54.96547880320569],[-1.492399924277289,54.965488765745555],[-1.495531694445359,54.96350639477768],[-1.495054005012269,54.963176180792665],[-1.4952488983587,54.96202214809809],[-1.494606515481112,54.96172884819366],[-1.494208559075658,54.96208193985043],[-1.493497273453704,54.96190802766432],[-1.493953089676043,54.961705654700125],[-1.493777571738164,54.96124738667174],[-1.49315350556053,54.961160499030676],[-1.493645238568877,54.96085364897213],[-1.494311401275041,54.96106748794554],[-1.494634590901919,54.960604794026395],[-1.495452099164438,54.96017907827976],[-1.49606573571814,54.96034344498439],[-1.497083490039855,54.96008280781371],[-1.496756624802035,54.95965392421537],[-1.495579659993754,54.95928639335611],[-1.494413653486565,54.95949221494366],[-1.493943477929195,54.959501315000324],[-1.492864083172857,54.95840947899351],[-1.492270924628742,54.958389034449446],[-1.493042842537736,54.95771326257199],[-1.494591849307221,54.95675419390663]],[[-1.494591849307221,54.95675419390663],[-1.494849851229258,54.956736689809226],[-1.497051782740566,54.95657228800111],[-1.51629366564802,54.95497595275669]],[[-1.51629366564802,54.95497595275669],[-1.515217297147246,54.956057919925335],[-1.515552332413502,54.95753245940884],[-1.516224419792536,54.95813778855547],[-1.516770423149119,54.95835861091886],[-1.518982723221074,54.95926467662063],[-1.519614930550891,54.95792338611301],[-1.519635752490773,54.95765880369071],[-1.522412868018255,54.957385987862864],[-1.523461392499871,54.95756532606699],[-1.525036339730896,54.95784792984959],[-1.526535855449262,54.957943179414684],[-1.527048949272236,54.95754495015715],[-1.527781452543995,54.95712384563854],[-1.529347046163149,54.957573052568996],[-1.529806093498648,54.95776660991572],[-1.529900701267711,54.95777944790885],[-1.530029235070814,54.957740799544624],[-1.530117366294877,54.95777200728545],[-1.53067710428188,54.95797024495247],[-1.530445469168618,54.958208585017864]],[[-1.439056472896785,54.9669558862279],[-1.438250694370478,54.96439571332366],[-1.437853083116117,54.96313577822003],[-1.437329893743017,54.96151645350347],[-1.437208226464513,54.96112034719784],[-1.436577753313107,54.95907599757082],[-1.436265280032358,54.95806116734452],[-1.435407056273336,54.95553365733164]],[[-1.435407056273336,54.95553365733164],[-1.4367564578313,54.95530685108775],[-1.436951994643866,54.955255123130996],[-1.436914716469246,54.955131531969684],[-1.43672561280112,54.9545816170805],[-1.436207562402953,54.953012283928395]],[[-1.436207562402953,54.953012283928395],[-1.443135047047159,54.95586969920877],[-1.447934627629606,54.95786017809762],[-1.452211556794178,54.959036051909365],[-1.453425206274188,54.959269066686886]],[[-1.453425206274188,54.959269066686886],[-1.456778912710124,54.959641118682214],[-1.460404742294523,54.959543264507474]],[[-1.471251286048276,54.958662516481084],[-1.472379427529827,54.95855997810584],[-1.473736036159113,54.957035566868896],[-1.474470337359791,54.957426102791494],[-1.474054655631079,54.95796487153683],[-1.476830516527647,54.9576928434771],[-1.475640117203374,54.95708153270224],[-1.475878325908149,54.95679825785147],[-1.477165992789609,54.95749837349225],[-1.477638178295254,54.95721283758996],[-1.478145539741905,54.95773357778135],[-1.478204597341409,54.9580779620984],[-1.481419479041298,54.957817028589425],[-1.483995024757288,54.95760917964982],[-1.486796737595482,54.9573793512121],[-1.487936922748515,54.95728652419593],[-1.487912278909869,54.956992361227464],[-1.487889233778383,54.95671738177041],[-1.489261713250104,54.95660707917857],[-1.489521152032039,54.95692306575313],[-1.490048374604258,54.95690035589515],[-1.492722759747391,54.956638882155],[-1.492774042759428,54.956881429870315],[-1.494591849307221,54.95675419390663]],[[-1.48042642098503,54.974948939959376],[-1.479374660884686,54.97519832189683],[-1.478754920205704,54.97576361603839]],[[-1.384095758134588,54.938654757205796],[-1.384275049051528,54.94511584830006],[-1.385918767678894,54.94603462335774],[-1.385910190892186,54.947013382827315],[-1.384092110322823,54.94721638552836]],[[-1.384092110322823,54.94721638552836],[-1.383629855567323,54.95147333093156],[-1.383205603045697,54.9514324449354],[-1.383056209467628,54.95276115115895],[-1.383192149843985,54.95486070136041],[-1.381752531276757,54.954810729025915],[-1.381559631021049,54.956020660868724],[-1.382472503554267,54.95638250192378],[-1.382434018027519,54.9590801775886],[-1.381927606380102,54.96126720118886],[-1.380842755240407,54.963262826589435],[-1.38162621627626,54.9637964464233],[-1.380652580274417,54.96424245566244],[-1.381468966541866,54.96570861188884],[-1.386693582231546,54.97083196713346],[-1.387037449841576,54.971432390321446],[-1.39285516035565,54.969684034241624],[-1.396695159271089,54.96929412105154],[-1.396499901450672,54.96898465238869]],[[-1.38089070092402,54.98025430318434],[-1.37849112330765,54.978716295338266],[-1.377659144775147,54.977655262101436],[-1.372323763016529,54.97473967147562],[-1.368435367324707,54.97383889036541],[-1.36728915454252,54.97291453986219],[-1.365327378263774,54.97309302747967],[-1.363833318231007,54.971844222416344],[-1.362011159040892,54.97178974486056],[-1.361498451403484,54.97112027553649],[-1.360740590612309,54.97133196333691],[-1.360789650081548,54.970898186267966],[-1.361708620953169,54.97047525990436],[-1.36148964974092,54.969802847736325],[-1.360490615326879,54.968873812902714],[-1.359946575133426,54.96890240228221],[-1.360284389836513,54.96789232985891],[-1.359558848065342,54.9677447308592],[-1.359560146452144,54.967368214368754],[-1.358543747286982,54.966849742602804],[-1.357705150011943,54.966741075445036],[-1.357446605602405,54.96620502789977],[-1.358070530320387,54.96586594737094],[-1.356689625812391,54.965289820067646],[-1.356864779524181,54.96478661814765],[-1.356346452037689,54.9641347090298],[-1.354994865027552,54.96139339075271],[-1.355652108528344,54.96092060387161],[-1.355125666381459,54.95887973072975],[-1.353279586415508,54.957628923552335],[-1.353451740321381,54.95743208714063],[-1.355487839647194,54.955665464071885],[-1.355381726624751,54.95448949659241],[-1.356933905598166,54.95350652627506],[-1.356107459376675,54.95050432979325],[-1.357526932098043,54.94898390782545],[-1.358036130566936,54.94822300786535],[-1.359871506232025,54.94767372487154],[-1.360548565088917,54.94652522322308],[-1.36317009914022,54.945022972160096],[-1.363969486729139,54.94411974945527],[-1.365715421379643,54.94417990794501],[-1.366151319384825,54.94286405953963],[-1.366728399696943,54.94291786158395],[-1.371834419527397,54.9433463362451],[-1.372160852792544,54.94336223249447],[-1.374248614447914,54.943521258108824],[-1.374475810702956,54.94303448469],[-1.374505945727779,54.94291535278633],[-1.375259196249856,54.93947706627677],[-1.37568332623464,54.93691020558663],[-1.376992196313337,54.937336445492754],[-1.378821356336645,54.936952048229415],[-1.379404425389439,54.937381864406206],[-1.381085829900564,54.93820031930234],[-1.384095758134588,54.938654757205796]],[[-1.413888481528719,54.963090750050945],[-1.413838706585077,54.96295876958922],[-1.413756885652931,54.96025708867547],[-1.422392290317644,54.959400237607824],[-1.422284159237243,54.959011617877344],[-1.424082139748697,54.958870294452645],[-1.424149846999657,54.958516872488524],[-1.424176889230979,54.95739445242458],[-1.42445761919785,54.95639451285871],[-1.426178196686511,54.955885917043865],[-1.427928783871403,54.95582520451409],[-1.43193614304628,54.95571056988604],[-1.432476482375933,54.955693877591536],[-1.435407056273336,54.95553365733164]],[[-1.471251286048276,54.958662516481084],[-1.472887999538675,54.95500833921348],[-1.473018738619758,54.9548001346748],[-1.473578123888808,54.9536787237655],[-1.473828632472223,54.952836690855655]],[[-1.473828632472223,54.952836690855655],[-1.474010403248559,54.95146770727988],[-1.473306566638046,54.94693203736409],[-1.473136593107872,54.94490129007474],[-1.473895363531847,54.94044176182119],[-1.473256777198588,54.93842888473691],[-1.471408956141838,54.93557729236358],[-1.46644755186333,54.93013917349895]],[[-1.46644755186333,54.93013917349895],[-1.471967929975826,54.929836930630955],[-1.480970298051381,54.92982623143042],[-1.48202338090101,54.928782137808184],[-1.483238878585553,54.92842054864401],[-1.485142358741052,54.92867012181685],[-1.488624298352287,54.9306213384654],[-1.492454647049891,54.930179070770926],[-1.496332244965052,54.93106403920344],[-1.500274328747922,54.930575366929915],[-1.505232075080008,54.93096405428144],[-1.508325111226936,54.930425621696436],[-1.510625404989993,54.930830285440074],[-1.511217513596326,54.93166603951966],[-1.510364653991376,54.93210359401973],[-1.515139321595767,54.94296180530801],[-1.51634358057307,54.94537942837736],[-1.517954054911193,54.946712381544366],[-1.518121766840098,54.947994985895654],[-1.518543674909463,54.95226544948294],[-1.51629366564802,54.95497595275669]],[[-1.453425206274188,54.959269066686886],[-1.452544455836941,54.954172517185064],[-1.448949725537431,54.953547214088395],[-1.44804502449767,54.95057847665315],[-1.447533625259885,54.949716009655646],[-1.4481057124713,54.947822538435204],[-1.448802139456863,54.94735142514049],[-1.450102354038036,54.94711455334064],[-1.451115501958471,54.94637691334046],[-1.451068175637709,54.94632134407482],[-1.451444402465701,54.94582250349664],[-1.453422125620493,54.945123332692425],[-1.453379561653748,54.94441076937327],[-1.456286527482165,54.94402702507918],[-1.456987997966592,54.944624133630555],[-1.45791213436504,54.94429105928762],[-1.459106461098072,54.944536809907184],[-1.460767096742783,54.944409787400346],[-1.462357176207283,54.94478218607292],[-1.462953424044628,54.9465252853562],[-1.46379862683891,54.94745248832156],[-1.462868421583005,54.94881825020323],[-1.463116889548005,54.94891819548498],[-1.465403824285577,54.94835313634667],[-1.469138061576812,54.946949642559844],[-1.471015030136408,54.94667923801197],[-1.472453637329933,54.94930351880933],[-1.471583045627345,54.94990880691664],[-1.471936481100635,54.950223836671036],[-1.472827018210445,54.951368960626304],[-1.473106004867436,54.952719241789445],[-1.473828632472223,54.952836690855655]],[[-1.384092110322823,54.94721638552836],[-1.39436485925344,54.94643901867166],[-1.394422169798865,54.946780790476375],[-1.396728907368336,54.9459924061239],[-1.402880949575461,54.94538221054526],[-1.40658488106864,54.94564530506449],[-1.40677154353577,54.94463074008742],[-1.40841387987535,54.944414052427035],[-1.413155991642777,54.94466161433901],[-1.414830131656329,54.945478433311436],[-1.418354998124444,54.947867687386825],[-1.416512207328013,54.94901990083212],[-1.416010812562837,54.949364073864004],[-1.41426277377148,54.950306699912225],[-1.415736131414451,54.95098786020877],[-1.417326692850927,54.950495137444456],[-1.41948053908741,54.951967380623834],[-1.419357329062129,54.95230649874561],[-1.422024084284316,54.952207657916745],[-1.420403000452318,54.94948728039433],[-1.420187040574244,54.948577385133746],[-1.421849863102319,54.948028146526845],[-1.422082222613267,54.94822184737032],[-1.422854835388073,54.94746800977595],[-1.425965409744094,54.948754180972],[-1.428925646375363,54.94999365166068],[-1.430056008257728,54.94897636122034],[-1.429380264931105,54.94873216014279],[-1.429146314793564,54.94804320128915],[-1.428171603414723,54.948193654046186],[-1.427719081499795,54.94744269132838],[-1.42688663188198,54.947735131754904],[-1.426555151729778,54.94761009614802],[-1.426847922025662,54.94733622411093],[-1.425363668222876,54.94678733085208],[-1.424587966854536,54.94729711675227],[-1.423016804710083,54.94709139530286],[-1.42323025113047,54.94677639288159],[-1.422576583253008,54.94672168129358],[-1.422548938001073,54.94622591479457],[-1.42282347932201,54.94603349898291],[-1.422046871259974,54.94542897935708],[-1.422468094962953,54.945244091334686],[-1.422216259953185,54.94496604189805],[-1.42486501274533,54.94408497028298],[-1.425964285123666,54.94399288026841],[-1.424691312967052,54.94365627063714],[-1.428339929590515,54.94284528433843],[-1.428792209787299,54.94325376544372],[-1.429571058018111,54.94326764985952],[-1.429674569878656,54.943572135330825],[-1.428651945212881,54.94412033551772],[-1.429298665226452,54.944603587054466],[-1.430463197084766,54.944672609512644],[-1.430103835397316,54.94505843502532],[-1.430379925015874,54.94617435194594],[-1.431393816411972,54.94627016595744],[-1.433658975216723,54.946941531934044],[-1.433129408850087,54.94763548770094],[-1.433570014860223,54.94771453607161],[-1.435971047812438,54.94750164817247],[-1.437154859364527,54.946563278703806],[-1.437287728926663,54.94720712627128],[-1.439309804559707,54.94771834997756],[-1.440014285051249,54.94763531727809],[-1.440251078214541,54.9485124034026],[-1.440260128042876,54.948545370949],[-1.441001149299978,54.95121988744034],[-1.440414717570193,54.95126747011718],[-1.437776168848621,54.95136767031973],[-1.43652484301239,54.95142310503683],[-1.435612779634136,54.95143853035486],[-1.436207562402953,54.953012283928395]],[[-1.384095758134588,54.938654757205796],[-1.38790930565071,54.9380313954091],[-1.390929711749525,54.938559942085305],[-1.391863155192988,54.93937924044135],[-1.393392938533644,54.93963865993914],[-1.398104807911823,54.939581129781104],[-1.402673817645326,54.93862910008281],[-1.406040128130527,54.937345626495045],[-1.407047610724067,54.93690932286288],[-1.410307289334102,54.93643987041937],[-1.412471872229373,54.93580666233279],[-1.417086847310249,54.93374960277332],[-1.418726978845866,54.93216460702387],[-1.41934257324731,54.92992038663172],[-1.420785207177835,54.929994911746924],[-1.426025345712493,54.93044703258006],[-1.426414491269254,54.93116834887306],[-1.427410135956284,54.93094099197203],[-1.431799811360553,54.92986147924066],[-1.432774820857562,54.93286691171534],[-1.441813539380029,54.932948883800016],[-1.442055590155369,54.93344230739797],[-1.447910554391936,54.93351058776679],[-1.449093639058644,54.934088260116795],[-1.452023596783197,54.93377541986808],[-1.452601078938001,54.933693547657214],[-1.456777184415989,54.93295569522638],[-1.460897922409237,54.932033288925524],[-1.460640435249002,54.930281505168956],[-1.461059015689601,54.93028630683797],[-1.46644755186333,54.93013917349895]]],"bbox":[-1.534172748300372,54.92842054864401,-1.353279586415508,55.011357079319474]}
